rcabench/__init__.py
rcabench/client/__init__.py
rcabench/client/http_client.py
rcabench/openapi/__init__.py
rcabench/openapi/api/__init__.py
rcabench/openapi/api/authentication_api.py
rcabench/openapi/api/containers_api.py
rcabench/openapi/api/datasets_api.py
rcabench/openapi/api/documentation_api.py
rcabench/openapi/api/evaluations_api.py
rcabench/openapi/api/executions_api.py
rcabench/openapi/api/injections_api.py
rcabench/openapi/api/projects_api.py
rcabench/openapi/api/system_api.py
rcabench/openapi/api/tasks_api.py
rcabench/openapi/api/traces_api.py
rcabench/openapi/api_client.py
rcabench/openapi/api_response.py
rcabench/openapi/configuration.py
rcabench/openapi/exceptions.py
rcabench/openapi/models/__init__.py
rcabench/openapi/models/batch_evaluate_datapack_req.py
rcabench/openapi/models/batch_evaluate_datapack_resp.py
rcabench/openapi/models/batch_evaluate_dataset_req.py
rcabench/openapi/models/batch_evaluate_dataset_resp.py
rcabench/openapi/models/batch_manage_injection_label_req.py
rcabench/openapi/models/batch_manage_injection_label_resp.py
rcabench/openapi/models/build_options.py
rcabench/openapi/models/building_spec.py
rcabench/openapi/models/chaos_chaos_resource_mapping.py
rcabench/openapi/models/chaos_chaos_type.py
rcabench/openapi/models/chaos_groundtruth.py
rcabench/openapi/models/chaos_node.py
rcabench/openapi/models/chaos_pair.py
rcabench/openapi/models/chaos_system_resource.py
rcabench/openapi/models/chaos_system_type.py
rcabench/openapi/models/container_detail_resp.py
rcabench/openapi/models/container_ref.py
rcabench/openapi/models/container_resp.py
rcabench/openapi/models/container_spec.py
rcabench/openapi/models/container_type.py
rcabench/openapi/models/container_version_detail_resp.py
rcabench/openapi/models/container_version_item.py
rcabench/openapi/models/container_version_resp.py
rcabench/openapi/models/create_container_req.py
rcabench/openapi/models/create_container_version_req.py
rcabench/openapi/models/create_dataset_req.py
rcabench-1.1.55.dist-info/WHEEL
rcabench-1.1.55.dist-info/METADATA
rcabench-1.1.55.dist-info/RECORD
