Metadata-Version: 2.4
Name: rcabench
Version: 1.1.55
Summary: RCABench - A comprehensive root cause analysis benchmarking platform for microservices
Author: Lincyaw, rainystevn1, YifanYang6
Author-email: Lincyaw <814750204@qq.com>, rainystevn1 <rainystevn1@gmail.com>, YifanYang6 <yifanyang6@link.cuhk.edu.cn>
License-Expression: Apache-2.0
Requires-Dist: setuptools>=75.6.0
Requires-Dist: tqdm>=4.67.1
Requires-Dist: twine>=5.1.1
Requires-Dist: wheel>=0.45.1
Requires-Dist: urllib3>=2.2.3,<3.0.0
Requires-Dist: python-dateutil>=2.9.0.post0
Requires-Dist: typing-extensions>=4.12.2
Requires-Dist: lazy-imports>=1.0.1
Requires-Dist: sseclient-py>=1.8.0
Requires-Dist: pydantic>=2.12.3
Requires-Dist: uv>=0.9.10
Requires-Python: >=3.10
Project-URL: Pypi, https://pypi.org/project/rcabench/
Project-URL: Repository, https://github.com/OperationsPAI/AegisLab
